{
    "candle": {
        "datetime": "2023-09-25-07-20",
        "open": "1925.955",
        "low": "1925.0149999999999",
        "high": "1926.015",
        "close": "1925.0149999999999"
    },
    "levels": [
        {
            "datetime": "2023-09-14-19-00",
            "pos": "BELOW",
            "price": "1908.3",
            "strength": "589"
        },
        {
            "datetime": "2023-09-14-19-45",
            "pos": "BELOW",
            "price": "1908.945",
            "strength": "586"
        },
        {
            "datetime": "2023-09-15-00-00",
            "pos": "BELOW",
            "price": "1909.9",
            "strength": "574"
        },
        {
            "datetime": "2023-09-15-00-30",
            "pos": "BELOW",
            "price": "1910.5",
            "strength": "572"
        },
        {
            "datetime": "2023-09-15-01-15",
            "pos": "BELOW",
            "price": "1911.105",
            "strength": "569"
        },
        {
            "datetime": "2023-09-15-03-15",
            "pos": "BELOW",
            "price": "1914.78",
            "strength": "561"
        },
        {
            "datetime": "2023-09-20-17-45",
            "pos": "ABOVE",
            "price": "1947.0",
            "strength": "230"
        },
        {
            "datetime": "2023-09-20-18-45",
            "pos": "ABOVE",
            "price": "1943.335",
            "strength": "226"
        },
        {
            "datetime": "2023-09-20-22-30",
            "pos": "ABOVE",
            "price": "1931.36",
            "strength": "216"
        },
        {
            "datetime": "2023-09-20-23-00",
            "pos": "ABOVE",
            "price": "1931.23",
            "strength": "214"
        },
        {
            "datetime": "2023-09-20-23-30",
            "pos": "ABOVE",
            "price": "1930.3000000000002",
            "strength": "212"
        },
        {
            "datetime": "2023-09-21-06-30",
            "pos": "ABOVE",
            "price": "1929.72",
            "strength": "184"
        },
        {
            "datetime": "2023-09-21-12-45",
            "pos": "BELOW",
            "price": "1914.9699999999998",
            "strength": "159"
        },
        {
            "datetime": "2023-09-21-13-15",
            "pos": "BELOW",
            "price": "1915.705",
            "strength": "157"
        },
        {
            "datetime": "2023-09-21-14-00",
            "pos": "BELOW",
            "price": "1916.555",
            "strength": "154"
        },
        {
            "datetime": "2023-09-21-16-15",
            "pos": "BELOW",
            "price": "1916.77",
            "strength": "145"
        },
        {
            "datetime": "2023-09-21-17-15",
            "pos": "BELOW",
            "price": "1919.44",
            "strength": "141"
        },
        {
            "datetime": "2023-09-21-20-15",
            "pos": "BELOW",
            "price": "1919.68",
            "strength": "129"
        },
        {
            "datetime": "2023-09-21-20-45",
            "pos": "BELOW",
            "price": "1919.93",
            "strength": "127"
        },
        {
            "datetime": "2023-09-21-23-00",
            "pos": "BELOW",
            "price": "1920.27",
            "strength": "123"
        },
        {
            "datetime": "2023-09-22-15-00",
            "pos": "ABOVE",
            "price": "1928.565",
            "strength": "59"
        },
        {
            "datetime": "2023-09-22-16-15",
            "pos": "ABOVE",
            "price": "1928.165",
            "strength": "54"
        },
        {
            "datetime": "2023-09-24-22-15",
            "pos": "ABOVE",
            "price": "1926.265",
            "strength": "35"
        },
        {
            "datetime": "2023-09-24-23-45",
            "pos": "ABOVE",
            "price": "1925.2199999999998",
            "strength": "29"
        },
        {
            "datetime": "2023-09-25-01-00",
            "pos": "ABOVE",
            "price": "1924.92",
            "strength": "24"
        },
        {
            "datetime": "2023-09-25-01-30",
            "pos": "ABOVE",
            "price": "1924.435",
            "strength": "22"
        },
        {
            "datetime": "2023-09-25-03-15",
            "pos": "ABOVE",
            "price": "1924.2350000000001",
            "strength": "15"
        }
    ],
    "signal": {
        "pos": "SHORT",
        "strength": "15"
    }
}