{
    "candle": {
        "datetime": "2024-02-02-15-25",
        "open": "2030.58",
        "low": "2029.745",
        "high": "2030.79",
        "close": "2029.745"
    },
    "levels": [
        {
            "datetime": "2024-01-24-20-00",
            "pos": "BELOW",
            "price": "2012.26",
            "strength": "617"
        },
        {
            "datetime": "2024-01-24-21-00",
            "pos": "BELOW",
            "price": "2012.345",
            "strength": "613"
        },
        {
            "datetime": "2024-01-24-21-45",
            "pos": "BELOW",
            "price": "2012.405",
            "strength": "610"
        },
        {
            "datetime": "2024-01-25-08-30",
            "pos": "BELOW",
            "price": "2013.51",
            "strength": "572"
        },
        {
            "datetime": "2024-01-25-09-15",
            "pos": "BELOW",
            "price": "2013.56",
            "strength": "569"
        },
        {
            "datetime": "2024-01-25-17-45",
            "pos": "BELOW",
            "price": "2013.745",
            "strength": "535"
        },
        {
            "datetime": "2024-01-25-19-00",
            "pos": "BELOW",
            "price": "2014.31",
            "strength": "530"
        },
        {
            "datetime": "2024-01-26-19-30",
            "pos": "BELOW",
            "price": "2016.25",
            "strength": "437"
        },
        {
            "datetime": "2024-01-26-20-00",
            "pos": "BELOW",
            "price": "2017.075",
            "strength": "435"
        },
        {
            "datetime": "2024-01-26-21-45",
            "pos": "BELOW",
            "price": "2018.42",
            "strength": "428"
        },
        {
            "datetime": "2024-01-29-15-30",
            "pos": "BELOW",
            "price": "2022.12",
            "strength": "362"
        },
        {
            "datetime": "2024-01-29-19-00",
            "pos": "BELOW",
            "price": "2025.885",
            "strength": "348"
        },
        {
            "datetime": "2024-01-29-19-30",
            "pos": "BELOW",
            "price": "2026.605",
            "strength": "346"
        },
        {
            "datetime": "2024-01-29-20-00",
            "pos": "BELOW",
            "price": "2027.09",
            "strength": "344"
        },
        {
            "datetime": "2024-02-01-16-45",
            "pos": "ABOVE",
            "price": "2063.44",
            "strength": "84"
        },
        {
            "datetime": "2024-02-01-17-15",
            "pos": "ABOVE",
            "price": "2061.02",
            "strength": "82"
        },
        {
            "datetime": "2024-02-01-19-15",
            "pos": "ABOVE",
            "price": "2057.95",
            "strength": "74"
        },
        {
            "datetime": "2024-02-02-08-15",
            "pos": "ABOVE",
            "price": "2056.785",
            "strength": "27"
        },
        {
            "datetime": "2024-02-02-13-15",
            "pos": "ABOVE",
            "price": "2056.325",
            "strength": "7"
        }
    ],
    "signal": "None"
}