{
    "candle": {
        "datetime": "2024-01-31-00-35",
        "open": "2037.2",
        "low": "2037.1799999999998",
        "high": "2037.27",
        "close": "2037.1799999999998",
        "type": {
            "hammer": 0.0,
            "inverted_hammer": 0.5555555555516256,
            "long_bar": 0.0
        },
        "color": {
            "red": 1,
            "green": 0
        }
    },
    "uptrend": 0,
    "downtrend": 1,
    "signal": {
        "Position": "FLAT",
        "SL": 0
    }
}