{
    "candle": {
        "datetime": "2023-09-26-09-15",
        "open": "1913.1",
        "low": "1913.0",
        "high": "1913.1100000000001",
        "close": "1913.0"
    },
    "levels": [
        {
            "datetime": "2023-09-14-19-00",
            "pos": "BELOW",
            "price": "1908.3",
            "strength": "687"
        },
        {
            "datetime": "2023-09-14-19-45",
            "pos": "BELOW",
            "price": "1908.945",
            "strength": "684"
        },
        {
            "datetime": "2023-09-15-00-00",
            "pos": "BELOW",
            "price": "1909.9",
            "strength": "672"
        },
        {
            "datetime": "2023-09-15-00-30",
            "pos": "BELOW",
            "price": "1910.5",
            "strength": "670"
        },
        {
            "datetime": "2023-09-20-17-45",
            "pos": "ABOVE",
            "price": "1947.0",
            "strength": "328"
        },
        {
            "datetime": "2023-09-20-18-45",
            "pos": "ABOVE",
            "price": "1943.335",
            "strength": "324"
        },
        {
            "datetime": "2023-09-20-22-30",
            "pos": "ABOVE",
            "price": "1931.36",
            "strength": "314"
        },
        {
            "datetime": "2023-09-20-23-00",
            "pos": "ABOVE",
            "price": "1931.23",
            "strength": "312"
        },
        {
            "datetime": "2023-09-20-23-30",
            "pos": "ABOVE",
            "price": "1930.3000000000002",
            "strength": "310"
        },
        {
            "datetime": "2023-09-21-06-30",
            "pos": "ABOVE",
            "price": "1929.72",
            "strength": "282"
        },
        {
            "datetime": "2023-09-22-15-00",
            "pos": "ABOVE",
            "price": "1928.565",
            "strength": "157"
        },
        {
            "datetime": "2023-09-22-16-15",
            "pos": "ABOVE",
            "price": "1928.165",
            "strength": "152"
        },
        {
            "datetime": "2023-09-25-07-15",
            "pos": "ABOVE",
            "price": "1926.9299999999998",
            "strength": "97"
        },
        {
            "datetime": "2023-09-25-12-45",
            "pos": "ABOVE",
            "price": "1926.365",
            "strength": "75"
        },
        {
            "datetime": "2023-09-25-14-00",
            "pos": "ABOVE",
            "price": "1925.785",
            "strength": "70"
        },
        {
            "datetime": "2023-09-25-15-45",
            "pos": "ABOVE",
            "price": "1918.375",
            "strength": "63"
        },
        {
            "datetime": "2023-09-25-17-30",
            "pos": "ABOVE",
            "price": "1917.495",
            "strength": "56"
        },
        {
            "datetime": "2023-09-25-22-30",
            "pos": "ABOVE",
            "price": "1916.775",
            "strength": "41"
        },
        {
            "datetime": "2023-09-25-23-15",
            "pos": "ABOVE",
            "price": "1916.59",
            "strength": "38"
        },
        {
            "datetime": "2023-09-26-07-00",
            "pos": "BELOW",
            "price": "1910.615",
            "strength": "8"
        }
    ],
    "signal": "None"
}