{
    "candle": {
        "datetime": "2024-02-02-12-50",
        "open": "2054.385",
        "low": "2054.375",
        "high": "2054.3900000000003",
        "close": "2054.3900000000003",
        "type": {
            "hammer": 0.33333333333333326,
            "inverted_hammer": 0.0,
            "long_bar": 0.0
        },
        "color": {
            "red": 0,
            "green": 1
        }
    },
    "uptrend": 0,
    "downtrend": 1,
    "signal": {
        "Position": "FLAT",
        "SL": 0
    }
}